HISTORY.rst
LICENSE
MANIFEST.in
README.rst
pluck.py
setup.py
pluck.egg-info/PKG-INFO
pluck.egg-info/SOURCES.txt
pluck.egg-info/dependency_links.txt
pluck.egg-info/top_level.txt